{
  "id": "1.2",
  "kind": "picture_answers",
  "scoreKind": "none",
  "dateRow": "<tr><td width='200'>Дата/специалист</td><td width='471'>{{DATE}}   {{USER}}</td></tr>",
  "initialBlock": "<tr><td width='200'>Результат: вывод об уровне развития</td><td width='471'><div contenteditable='true'></div></td></tr><tr><td width='200'>Примечание</td><td width='471'><div contenteditable='true'></div></td></tr><tr><td align='center' colspan='2'>Процесс выполнения диагностической методики</td></tr></table><!--s--><table border='1' style='table-layout:fixed' cellspacing='0' cellpadding='0' width='671'><tr><td width='229' align='center'>Картинка(описание)</td><td width='88' align='center'>Уровень выполнения</td><td width='160' align='center'>Характер деятельности ребенка</td><td width='194' align='center'>Виды помощи</td></tr>",
  "rowTemplate": "<tr><td>1. Бабушка на диване без ножки.</td><td valign='top'>{{RESULT}}</td><td valign='top' rowspan='5'><div contenteditable='true' style='text-align:left'>{{OR}}</div></td><td valign='top' rowspan='5'><div contenteditable='true' style='text-align:left'>{{HLP}}</div></td></tr><tr><td>2. Велосипедист без переднего колеса.</td><td valign='top'>{{RESULT}}</td></tr><tr><td>3. Девочка с расческой без зубчиков.</td><td valign='top'>{{RESULT}}</td></tr><tr><td>4. Пальто без рукава.</td><td>{{RESULT}}</td></tr><tr><td>5. Ослик без уха.</td><td>{{RESULT}}</td></tr>"
}
